{
  "sections": {
    "main": {
      "type": "main-product",
      "blocks": {
        "title": {
          "type": "title",
          "settings": {
            "heading_tag": "h3"
          }
        },
        "judge_me_reviews_preview_badge_injcPY": {
          "type": "shopify:\/\/apps\/judge-me-reviews\/blocks\/preview_badge\/61ccd3b1-a9f2-4160-9fe9-4fec8413e5d8",
          "settings": {}
        },
        "price": {
          "type": "price",
          "settings": {
            "show_taxes_notice": true
          }
        },
        "variant_picker": {
          "type": "variant_picker",
          "settings": {
            "hide_sold_out_variants": false,
            "selector_style": "block",
            "swatch_selector_style": "swatch",
            "variant_image_options": "",
            "size_chart_page": ""
          }
        },
        "buy_buttons_pndJea": {
          "type": "buy_buttons",
          "settings": {
            "show_payment_button": false,
            "show_gift_card_recipient": true,
            "atc_button_background": "",
            "atc_button_text_color": "",
            "payment_button_background": "",
            "payment_button_text_color": ""
          }
        },
        "separator": {
          "type": "separator",
          "settings": {}
        },
        "description": {
          "type": "description",
          "settings": {
            "collapse_content": true,
            "show_below_gallery": true
          }
        },
        "accordion_gzMED9": {
          "type": "accordion",
          "settings": {
            "show_below_gallery": true,
            "icon": "none",
            "title": "HOW TO USE",
            "content": "{{ product.metafields.custom.how_to_use | metafield_tag }}",
            "liquid": "",
            "page": ""
          }
        },
        "instafeed_app_block_BA3QkY": {
          "type": "shopify:\/\/apps\/instafeed\/blocks\/app-block\/c447db20-095d-4a10-9725-b5977662c9d5",
          "settings": {
            "title": "",
            "title_color": "",
            "alignment": "center",
            "background_color": "",
            "feed_id": "38139",
            "html_area": ""
          }
        },
        "accordion_XV34U8": {
          "type": "accordion",
          "settings": {
            "show_below_gallery": true,
            "icon": "none",
            "title": "INGREDIENTS",
            "content": "<p><\/p>{{ product.metafields.custom.ingredients_tab | metafield_tag }}",
            "liquid": "",
            "page": ""
          }
        },
        "accordion_MVKVCD": {
          "type": "accordion",
          "settings": {
            "show_below_gallery": true,
            "icon": "none",
            "title": "Frequently Asked Questions",
            "content": "{{ product.metafields.custom.faq | metafield_tag }}",
            "liquid": "",
            "page": ""
          }
        },
        "accordion_Lp8CND": {
          "type": "accordion",
          "settings": {
            "show_below_gallery": true,
            "icon": "none",
            "title": "Additional Details",
            "content": "{{ product.metafields.custom.additional_details | metafield_tag }}",
            "liquid": "",
            "page": ""
          }
        },
        "separator_MpXe6H": {
          "type": "separator",
          "settings": {}
        },
        "complementary_products": {
          "type": "complementary_products",
          "disabled": true,
          "settings": {
            "title": "Pairs well with",
            "products_count": 2,
            "show_below_gallery": true,
            "stack_products": false,
            "show_quick_buy": true
          }
        }
      },
      "block_order": [
        "title",
        "judge_me_reviews_preview_badge_injcPY",
        "price",
        "variant_picker",
        "buy_buttons_pndJea",
        "separator",
        "description",
        "accordion_gzMED9",
        "instafeed_app_block_BA3QkY",
        "accordion_XV34U8",
        "accordion_MVKVCD",
        "accordion_Lp8CND",
        "separator_MpXe6H",
        "complementary_products"
      ],
      "custom_css": [
        "@media only screen and (max-width: 768px) {.jdgm-widget.jdgm-widget {text-align: center; }}"
      ],
      "settings": {
        "color_scheme": "scheme-1",
        "container_size": "lg",
        "product_info_size": 50,
        "show_sticky_add_to_cart": true,
        "center_basic_info": true,
        "desktop_media_layout": "carousel_dots",
        "desktop_media_grid_gap": 30,
        "mobile_controls": "dots",
        "enable_media_autoplay": true,
        "enable_video_looping": true,
        "enable_image_zoom": true,
        "max_image_zoom_level": 2
      }
    },
    "related-products": {
      "type": "related-products",
      "settings": {
        "color_scheme": "",
        "separate_section_with_border": true,
        "hide_product_information": false,
        "stack_products": false,
        "recommendations_count": 10,
        "products_per_row_mobile": "2",
        "products_per_row_desktop": 4,
        "horizontal_spacing_factor": 1,
        "vertical_spacing_factor": 1,
        "subheading": "",
        "title": "Related products",
        "content": ""
      }
    },
    "1734606047e147cdf1": {
      "type": "apps",
      "blocks": {
        "judge_me_reviews_review_widget_rthEFy": {
          "type": "shopify:\/\/apps\/judge-me-reviews\/blocks\/review_widget\/61ccd3b1-a9f2-4160-9fe9-4fec8413e5d8",
          "settings": {}
        }
      },
      "block_order": [
        "judge_me_reviews_review_widget_rthEFy"
      ],
      "settings": {
        "color_scheme": "",
        "separate_section_with_border": true,
        "remove_vertical_spacing": false,
        "remove_horizontal_spacing": false
      }
    }
  },
  "order": [
    "main",
    "related-products",
    "1734606047e147cdf1"
  ]
}
